PyImageLabeling/__init__.py
PyImageLabeling/__main__.py
PyImageLabeling/config.json
PyImageLabeling/parameters.json
PyImageLabeling/style.css
PyImageLabeling/controller/Controller.py
PyImageLabeling/controller/Events.py
PyImageLabeling/controller/FileEvents.py
PyImageLabeling/controller/ImageEvents.py
PyImageLabeling/controller/LabelEvents.py
PyImageLabeling/controller/LabelingEvents.py
PyImageLabeling/controller/settings/ContourFillinSetting.py
PyImageLabeling/controller/settings/CoutourFillingApplyCancel.py
PyImageLabeling/controller/settings/EraserSetting.py
PyImageLabeling/controller/settings/LabelSetting.py
PyImageLabeling/controller/settings/MagicPenSetting.py
PyImageLabeling/controller/settings/OpacitySetting.py
PyImageLabeling/controller/settings/PaintBrushSetting.py
PyImageLabeling/icons/apply.png
PyImageLabeling/icons/asterisk-green.png
PyImageLabeling/icons/asterisk-red.png
PyImageLabeling/icons/back.png
PyImageLabeling/icons/border.png
PyImageLabeling/icons/cancel.png
PyImageLabeling/icons/cleaner.png
PyImageLabeling/icons/close.png
PyImageLabeling/icons/down.png
PyImageLabeling/icons/ellipse.png
PyImageLabeling/icons/eraser.png
PyImageLabeling/icons/eraser_tool.png
PyImageLabeling/icons/filling.png
PyImageLabeling/icons/filling_mousse.png
PyImageLabeling/icons/filling_tool.png
PyImageLabeling/icons/logoMAIA.png
PyImageLabeling/icons/magic.png
PyImageLabeling/icons/magic_tool.png
PyImageLabeling/icons/maia.png
PyImageLabeling/icons/maia1.png
PyImageLabeling/icons/maia3.ico
PyImageLabeling/icons/maia_icon.png
PyImageLabeling/icons/move.png
PyImageLabeling/icons/opacity.png
PyImageLabeling/icons/open_image.png
PyImageLabeling/icons/open_layer.png
PyImageLabeling/icons/paint.png
PyImageLabeling/icons/paint_tool.png
PyImageLabeling/icons/plus.png
PyImageLabeling/icons/polygon.png
PyImageLabeling/icons/rectangle.png
PyImageLabeling/icons/reset.png
PyImageLabeling/icons/save.png
PyImageLabeling/icons/save_copy.png
PyImageLabeling/icons/setting.png
pyimagelabeling-1.0.5.dist-info/licenses/LICENCE
pyimagelabeling-1.0.5.dist-info/METADATA
pyimagelabeling-1.0.5.dist-info/WHEEL
pyimagelabeling-1.0.5.dist-info/top_level.txt
pyimagelabeling-1.0.5.dist-info/RECORD
