Metadata-Version: 2.4
Name: PyImageLabeling
Version: 1.0.5
Summary: PyImageLabeling is a tool designed to help create image masks, i.e., labeled images for training machine learning models.
Author-email: Szczepanski Nicolas <szczepanski@cril.fr>, Fayette Pierre-Marie <pmarie.fayette@univ-artois.fr>
Maintainer-email: Szczepanski Nicolas <szczepanski@cril.fr>, Fayette Pierre-Marie <pmarie.fayette@univ-artois.fr>
License: MIT
Project-URL: Git, https://github.com/crillab/PyImageLabeling
Keywords: AI,ML,labeling,learning,image
Classifier: Topic :: Scientific/Engineering :: Artificial Intelligence
Classifier: Topic :: Education
Requires-Python: >=3.12
License-File: LICENCE
Requires-Dist: numpy
Requires-Dist: pyqt6
Requires-Dist: opencv-python
Requires-Dist: pillow
Requires-Dist: matplotlib
Dynamic: license-file
